LICENSE
MANIFEST.in
README.md
setup.py
FAYAAEE/Faab.py
FAYAAEE/FaabFunction.py
FAYAAEE/FaabJWT.py
FAYAAEE/__init__.py
FAYAAEE/__version__.py
FAYAAEE/extensions.py
FAYAAEE/factory.py
FAYAAEE/utils.py
FAYAAEE.egg-info/PKG-INFO
FAYAAEE.egg-info/SOURCES.txt
FAYAAEE.egg-info/dependency_links.txt
FAYAAEE.egg-info/requires.txt
FAYAAEE.egg-info/top_level.txt
FAYAAEE/swag_config/__init__.py