Metadata-Version: 2.1
Name: FAYAAEE
Version: 1.2.0
Summary: An Amazing Tool.
Home-page: 
Author: Mao
Author-email: 
License: GLP
Classifier: Programming Language :: Python
Classifier: Programming Language :: Python :: 3
Classifier: Programming Language :: Python :: 3.6
Classifier: Programming Language :: Python :: Implementation :: CPython
Classifier: Programming Language :: Python :: Implementation :: PyPy
Requires-Python: >=3.6.0
License-File: LICENSE
Requires-Dist: flask
Requires-Dist: flask-sqlalchemy
Requires-Dist: pymysql
Requires-Dist: PyJWT
Requires-Dist: Flask-Cors
Requires-Dist: Pillow
Requires-Dist: ffmpeg-python
Requires-Dist: werkzeug
